odoo/addons/website_sale_b2x_alt_price/README.rst
odoo/addons/website_sale_b2x_alt_price/__init__.py
odoo/addons/website_sale_b2x_alt_price/__manifest__.py
odoo/addons/website_sale_b2x_alt_price/demo/assets.xml
odoo/addons/website_sale_b2x_alt_price/i18n/es.po
odoo/addons/website_sale_b2x_alt_price/i18n/website_sale_b2x_alt_price.pot
odoo/addons/website_sale_b2x_alt_price/models/__init__.py
odoo/addons/website_sale_b2x_alt_price/models/product_template.py
odoo/addons/website_sale_b2x_alt_price/readme/CONFIGURE.rst
odoo/addons/website_sale_b2x_alt_price/readme/CONTRIBUTORS.rst
odoo/addons/website_sale_b2x_alt_price/readme/DESCRIPTION.rst
odoo/addons/website_sale_b2x_alt_price/readme/ROADMAP.rst
odoo/addons/website_sale_b2x_alt_price/readme/USAGE.rst
odoo/addons/website_sale_b2x_alt_price/static/description/b2b-features.png
odoo/addons/website_sale_b2x_alt_price/static/description/b2c-features.png
odoo/addons/website_sale_b2x_alt_price/static/description/details-features.gif
odoo/addons/website_sale_b2x_alt_price/static/description/icon.png
odoo/addons/website_sale_b2x_alt_price/static/description/index.html
odoo/addons/website_sale_b2x_alt_price/static/description/toggle-detail.gif
odoo/addons/website_sale_b2x_alt_price/static/description/toggle-list.gif
odoo/addons/website_sale_b2x_alt_price/static/src/js/product_configurator_mixin.js
odoo/addons/website_sale_b2x_alt_price/static/tours/b2b.js
odoo/addons/website_sale_b2x_alt_price/static/tours/b2c.js
odoo/addons/website_sale_b2x_alt_price/templates/assets.xml
odoo/addons/website_sale_b2x_alt_price/templates/product.xml
odoo/addons/website_sale_b2x_alt_price/tests/__init__.py
odoo/addons/website_sale_b2x_alt_price/tests/test_ui.py
odoo12_addon_website_sale_b2x_alt_price-12.0.1.0.1.dist-info/METADATA
odoo12_addon_website_sale_b2x_alt_price-12.0.1.0.1.dist-info/WHEEL
odoo12_addon_website_sale_b2x_alt_price-12.0.1.0.1.dist-info/top_level.txt
odoo12_addon_website_sale_b2x_alt_price-12.0.1.0.1.dist-info/RECORD
